prophet/__init__.py
prophet/__version__.py
prophet/diagnostics.py
prophet/forecaster.py
prophet/hdays.py
prophet/make_holidays.py
prophet/models.py
prophet/plot.py
prophet/serialize.py
prophet/tests/__init__.py
prophet/tests/conftest.py
prophet/tests/data.csv
prophet/tests/data2.csv
prophet/tests/serialized_model_v0.6.1.dev0.json
prophet/tests/serialized_model_v0.7.1.json
prophet/tests/serialized_model_v1.0.1.json
prophet/tests/test_diagnostics.py
prophet/tests/test_prophet.py
prophet/tests/test_serialize.py
prophet/tests/test_utilities.py
prophet/utilities.py
cuprophet-0.1.6.dist-info/METADATA
cuprophet-0.1.6.dist-info/WHEEL
cuprophet-0.1.6.dist-info/RECORD
