Metadata-Version: 2.1
Name: cuprophet
Version: 0.1.6
Summary: 
Author: StoffAudioLLC
Author-email: stoffaudio@gmail.com
Requires-Python: >=3.9,<4.0
Classifier: Programming Language :: Python :: 3
Classifier: Programming Language :: Python :: 3.9
Classifier: Programming Language :: Python :: 3.10
Classifier: Programming Language :: Python :: 3.11
Requires-Dist: LunarCalendar (>=0.0.9,<0.0.10)
Requires-Dist: cmdstanpy-opencl (>=0.9.70,<0.10.0)
Requires-Dist: convertdate (>=2.1.2,<3.0.0)
Requires-Dist: holidays (>=0.14.2,<0.15.0)
Requires-Dist: importlib_resources
Requires-Dist: matplotlib
Requires-Dist: numpy (>=1.15.4,<2.0.0)
Requires-Dist: pandas (>=1.0.4,<2.0.0)
Requires-Dist: python-dateutil (>=2.8.0,<3.0.0)
Requires-Dist: tqdm (>=4.36.1,<5.0.0)
